MANIFEST.in
README.rst
bootstrap.py
buildout.cfg
setup.py
collective/__init__.py
collective.django.egg-info/PKG-INFO
collective.django.egg-info/SOURCES.txt
collective.django.egg-info/dependency_links.txt
collective.django.egg-info/entry_points.txt
collective.django.egg-info/namespace_packages.txt
collective.django.egg-info/not-zip-safe
collective.django.egg-info/requires.txt
collective.django.egg-info/top_level.txt
collective/django/__init__.py
collective/django/configure.zcml
collective/django/directives.py
collective/django/manager.py
collective/django/meta.zcml
collective/django/tests/__init__.py
collective/django/tests/layers.py
collective/django/tests/test_simple.py
collective/django/tests/dummies/dummypackage/setup.py
collective/django/tests/dummies/dummypackage/dummypackage/__init__.py
collective/django/tests/dummies/dummypackage/dummypackage/models.py
collective/django/tests/dummies/dummyproject/setup.py
collective/django/tests/dummies/dummyproject/dummyproject/__init__.py
collective/django/tests/dummies/dummyproject/dummyproject/settings.py
collective/django/tests/dummies/dummyproject/dummyproject/urls.py
docs/CHANGELOG.rst
docs/CONTRIBUTORS.rst
docs/INTERNALS.rst
docs/LICENSE.txt