Metadata-Version: 1.0
Name: collective.django
Version: 0.2
Summary: Django transaction integration for Plone
Home-page: http://github.com/collective/collective.django
Author: Simone Deponti
Author-email: simone.deponti@abstract.it
License: BSD
Platform: UNKNOWN
Classifier: Environment :: Web Environment
Classifier: Framework :: Django
Classifier: Framework :: Plone
Classifier: Intended Audience :: Developers
Classifier: License :: OSI Approved :: BSD License
